mathesis/_utils.py
mathesis/deduction/hilbert/axioms.py
mathesis/deduction/hilbert/hilbert.py
mathesis/deduction/hilbert/rules.py
mathesis/deduction/natural_deduction/__init__.py
mathesis/deduction/natural_deduction/natural_deduction.py
mathesis/deduction/natural_deduction/rules.py
mathesis/deduction/sequent_calculus/__init__.py
mathesis/deduction/sequent_calculus/rules.py
mathesis/deduction/sequent_calculus/sequent.py
mathesis/deduction/sequent_calculus/sequent_tree.py
mathesis/deduction/tableau/__init__.py
mathesis/deduction/tableau/rules.py
mathesis/deduction/tableau/signed_rules.py
mathesis/deduction/tableau/tableau.py
mathesis/forms.py
mathesis/grammars.py
mathesis/semantics/model.py
mathesis/semantics/truth_table/__init__.py
mathesis/semantics/truth_table/base.py
mathesis/semantics/truth_table/classical.py
mathesis/semantics/truth_table/fde.py
mathesis/semantics/truth_table/k3.py
mathesis/semantics/truth_table/l3.py
mathesis/semantics/truth_table/lp.py
mathesis/solvers.py
mathesis/system/classical/__init__.py
mathesis/system/classical/truth_table.py
mathesis/system/intuitionistic/__init__.py
mathesis/system/intuitionistic/sequent_calculus/__init__.py
mathesis/system/intuitionistic/sequent_calculus/rules.py
mathesis/truth_values/__init__.py
mathesis/truth_values/boolean.py
mathesis/truth_values/numeric.py
mathesis-0.7.2.dist-info/METADATA
mathesis-0.7.2.dist-info/WHEEL
mathesis-0.7.2.dist-info/licenses/LICENSE.md
mathesis-0.7.2.dist-info/RECORD
