Metadata-Version: 2.4
Name: mathesis
Version: 0.7.2
Summary: Formal logic library in Python for humans
License-Expression: MIT
License-File: LICENSE.md
Keywords: logic,semantics,proof,philosophy
Author: Kentaro Ozeki
Author-email: 32771324+ozekik@users.noreply.github.com
Requires-Python: >=3.10,<4.0
Classifier: Programming Language :: Python :: 3
Classifier: Programming Language :: Python :: 3.10
Classifier: Programming Language :: Python :: 3.11
Classifier: Programming Language :: Python :: 3.12
Classifier: Programming Language :: Python :: 3.13
Classifier: Programming Language :: Python :: 3.14
Requires-Dist: anytree (>=2.8.0,<3.0.0)
Requires-Dist: lark (>=1.1.2,<2.0.0)
Requires-Dist: prettytable (>=3.3.0,<4.0.0)
Project-URL: Homepage, https://digitalformallogic.github.io/mathesis/
Project-URL: Repository, https://github.com/digitalformallogic/mathesis
